{
  "version": 4,
  "routes": {
    "/confidentialite": {
      "experimentalBypassFor": [
        {
          "type": "header",
          "key": "next-action"
        },
        {
          "type": "header",
          "key": "content-type",
          "value": "multipart/form-data;.*"
        }
      ],
      "initialRevalidateSeconds": false,
      "srcRoute": "/confidentialite",
      "dataRoute": "/confidentialite.rsc",
      "allowHeader": [
        "host",
        "x-matched-path",
        "x-prerender-revalidate",
        "x-prerender-revalidate-if-generated",
        "x-next-revalidated-tags",
        "x-next-revalidate-tag-token"
      ]
    },
    "/chambres": {
      "experimentalBypassFor": [
        {
          "type": "header",
          "key": "next-action"
        },
        {
          "type": "header",
          "key": "content-type",
          "value": "multipart/form-data;.*"
        }
      ],
      "initialRevalidateSeconds": false,
      "srcRoute": "/chambres",
      "dataRoute": "/chambres.rsc",
      "allowHeader": [
        "host",
        "x-matched-path",
        "x-prerender-revalidate",
        "x-prerender-revalidate-if-generated",
        "x-next-revalidated-tags",
        "x-next-revalidate-tag-token"
      ]
    },
    "/favicon.ico": {
      "initialHeaders": {
        "cache-control": "public, max-age=0, must-revalidate",
        "content-type": "image/x-icon",
        "x-next-cache-tags": "_N_T_/layout,_N_T_/favicon.ico/layout,_N_T_/favicon.ico/route,_N_T_/favicon.ico"
      },
      "experimentalBypassFor": [
        {
          "type": "header",
          "key": "next-action"
        },
        {
          "type": "header",
          "key": "content-type",
          "value": "multipart/form-data;.*"
        }
      ],
      "initialRevalidateSeconds": false,
      "srcRoute": "/favicon.ico",
      "dataRoute": null,
      "allowHeader": [
        "host",
        "x-matched-path",
        "x-prerender-revalidate",
        "x-prerender-revalidate-if-generated",
        "x-next-revalidated-tags",
        "x-next-revalidate-tag-token"
      ]
    },
    "/contact": {
      "experimentalBypassFor": [
        {
          "type": "header",
          "key": "next-action"
        },
        {
          "type": "header",
          "key": "content-type",
          "value": "multipart/form-data;.*"
        }
      ],
      "initialRevalidateSeconds": false,
      "srcRoute": "/contact",
      "dataRoute": "/contact.rsc",
      "allowHeader": [
        "host",
        "x-matched-path",
        "x-prerender-revalidate",
        "x-prerender-revalidate-if-generated",
        "x-next-revalidated-tags",
        "x-next-revalidate-tag-token"
      ]
    },
    "/": {
      "experimentalBypassFor": [
        {
          "type": "header",
          "key": "next-action"
        },
        {
          "type": "header",
          "key": "content-type",
          "value": "multipart/form-data;.*"
        }
      ],
      "initialRevalidateSeconds": false,
      "srcRoute": "/",
      "dataRoute": "/index.rsc",
      "allowHeader": [
        "host",
        "x-matched-path",
        "x-prerender-revalidate",
        "x-prerender-revalidate-if-generated",
        "x-next-revalidated-tags",
        "x-next-revalidate-tag-token"
      ]
    },
    "/reservation": {
      "experimentalBypassFor": [
        {
          "type": "header",
          "key": "next-action"
        },
        {
          "type": "header",
          "key": "content-type",
          "value": "multipart/form-data;.*"
        }
      ],
      "initialRevalidateSeconds": false,
      "srcRoute": "/reservation",
      "dataRoute": "/reservation.rsc",
      "allowHeader": [
        "host",
        "x-matched-path",
        "x-prerender-revalidate",
        "x-prerender-revalidate-if-generated",
        "x-next-revalidated-tags",
        "x-next-revalidate-tag-token"
      ]
    },
    "/_not-found": {
      "initialStatus": 404,
      "experimentalBypassFor": [
        {
          "type": "header",
          "key": "next-action"
        },
        {
          "type": "header",
          "key": "content-type",
          "value": "multipart/form-data;.*"
        }
      ],
      "initialRevalidateSeconds": false,
      "srcRoute": "/_not-found",
      "dataRoute": "/_not-found.rsc",
      "allowHeader": [
        "host",
        "x-matched-path",
        "x-prerender-revalidate",
        "x-prerender-revalidate-if-generated",
        "x-next-revalidated-tags",
        "x-next-revalidate-tag-token"
      ]
    },
    "/avis": {
      "experimentalBypassFor": [
        {
          "type": "header",
          "key": "next-action"
        },
        {
          "type": "header",
          "key": "content-type",
          "value": "multipart/form-data;.*"
        }
      ],
      "initialRevalidateSeconds": false,
      "srcRoute": "/avis",
      "dataRoute": "/avis.rsc",
      "allowHeader": [
        "host",
        "x-matched-path",
        "x-prerender-revalidate",
        "x-prerender-revalidate-if-generated",
        "x-next-revalidated-tags",
        "x-next-revalidate-tag-token"
      ]
    },
    "/services": {
      "experimentalBypassFor": [
        {
          "type": "header",
          "key": "next-action"
        },
        {
          "type": "header",
          "key": "content-type",
          "value": "multipart/form-data;.*"
        }
      ],
      "initialRevalidateSeconds": false,
      "srcRoute": "/services",
      "dataRoute": "/services.rsc",
      "allowHeader": [
        "host",
        "x-matched-path",
        "x-prerender-revalidate",
        "x-prerender-revalidate-if-generated",
        "x-next-revalidated-tags",
        "x-next-revalidate-tag-token"
      ]
    },
    "/conditions": {
      "experimentalBypassFor": [
        {
          "type": "header",
          "key": "next-action"
        },
        {
          "type": "header",
          "key": "content-type",
          "value": "multipart/form-data;.*"
        }
      ],
      "initialRevalidateSeconds": false,
      "srcRoute": "/conditions",
      "dataRoute": "/conditions.rsc",
      "allowHeader": [
        "host",
        "x-matched-path",
        "x-prerender-revalidate",
        "x-prerender-revalidate-if-generated",
        "x-next-revalidated-tags",
        "x-next-revalidate-tag-token"
      ]
    }
  },
  "dynamicRoutes": {},
  "notFoundRoutes": [],
  "preview": {
    "previewModeId": "fdb3d70954341321a0bebb5ba9899cf6",
    "previewModeSigningKey": "5ba8f8d5a9023fb4092e64391e36d8246290ff21261b0a8cf755f8eef713cb11",
    "previewModeEncryptionKey": "653256d3c0d76a2e269441162ddeb0f3147a0a7c9f4dc48997e097bf53829cc2"
  }
}